lm_pelican_engrave-0.1.1.dist-info/METADATA
lm_pelican_engrave-0.1.1.dist-info/WHEEL
lm_pelican_engrave-0.1.1.dist-info/licenses/LICENSE
pelican/plugins/lm_pelican_engrave/__init__.py
pelican/plugins/lm_pelican_engrave/engrave.py
pelican/plugins/lm_pelican_engrave/engraver/__init__.py
pelican/plugins/lm_pelican_engrave/engraver/qrcode.py
pelican/plugins/lm_pelican_engrave/engraver/template.py
pelican/plugins/lm_pelican_engrave/tests/__init__.py
pelican/plugins/lm_pelican_engrave/tests/test_engrave.py
pelican/plugins/lm_pelican_engrave/tests/test_engraver/__init__.py
pelican/plugins/lm_pelican_engrave/tests/test_engraver/test_qrcode.py
pelican/plugins/lm_pelican_engrave/tests/test_engraver/test_template.py
lm_pelican_engrave-0.1.1.dist-info/RECORD
