Metadata-Version: 2.1
Name: lm-pelican-engrave
Version: 0.1.1
Summary: A plugin for generating and embedding QR codes in your blogpost
Keywords: pelican,plugin,qrcode,qr,blog,url
Author-Email: Lukas Muenter <lukas.muenter@protonmail.com>
License: MIT
Classifier: Development Status :: 1 - Planning
Classifier: Environment :: Console
Classifier: Framework :: Pelican
Classifier: Framework :: Pelican :: Plugins
Classifier: Intended Audience :: End Users/Desktop
Classifier: License :: OSI Approved :: MIT License
Classifier: Operating System :: OS Independent
Classifier: Programming Language :: Python :: 3
Classifier: Programming Language :: Python :: 3.8
Classifier: Programming Language :: Python :: 3.9
Classifier: Programming Language :: Python :: 3.10
Classifier: Programming Language :: Python :: 3.11
Classifier: Programming Language :: Python :: 3.12
Classifier: Topic :: Internet :: WWW/HTTP
Classifier: Topic :: Software Development :: Libraries :: Python Modules
Project-URL: Homepage, https://github.com/lmuenter/pelican-engrave
Project-URL: Issue tracker, https://github.com/lmuenter/pelican-engrave/issues
Project-URL: Funding, https://donate.getpelican.com/
Requires-Python: <4.0,>=3.8.1
Requires-Dist: pelican>=4.5
Requires-Dist: qrcode[pil]>=7.0
Requires-Dist: markdown>=3.4; extra == "markdown"
Provides-Extra: markdown
